eisen_cli/__init__.py
eisen_cli/main.py
eisen_cli/utils.py
eisen_cli/serve/__init__.py
eisen_cli/test/__init__.py
eisen_cli/test/test.py
eisen_cli/train/__init__.py
eisen_cli/train/train.py
eisen_cli/validate/__init__.py
eisen_cli/validate/validate.py
eisen_cli-0.0.7.dist-info/LICENSE
eisen_cli-0.0.7.dist-info/METADATA
eisen_cli-0.0.7.dist-info/WHEEL
eisen_cli-0.0.7.dist-info/entry_points.txt
eisen_cli-0.0.7.dist-info/top_level.txt
eisen_cli-0.0.7.dist-info/RECORD
